{
	"interactionModel": {
		"languageModel": {
			"invocationName": "medida exacta",
			"intents": [
				{
					"name": "AMAZON.CancelIntent",
					"samples": []
				},
				{
					"name": "AMAZON.HelpIntent",
					"samples": []
				},
				{
					"name": "AMAZON.StopIntent",
					"samples": []
				},
				{
					"name": "AMAZON.NavigateHomeIntent",
					"samples": []
				},
				{
					"name": "AMAZON.FallbackIntent",
					"samples": []
				},
				{
					"name": "WithoutDecimal",
					"slots": [
						{
							"name": "inputValue",
							"type": "AMAZON.NUMBER"
						},
						{
							"name": "sourceType",
							"type": "measuretype"
						},
						{
							"name": "destType",
							"type": "measuretype"
						}
					],
					"samples": [
						"{inputValue} {sourceType} to {destType} ",
						"{inputValue} {sourceType} into {destType} ",
						"{inputValue} {sourceType} in {destType} ",
						"for {inputValue} {sourceType} in {destType} ",
						"to change {inputValue} {sourceType} to {destType}",
						"to give me {inputValue} {sourceType} in {destType}",
						"to convert {inputValue} {sourceType} to {destType}",
						"to tell me what {inputValue} {sourceType} in {destType} is",
						"give me {inputValue} {sourceType} in {destType}",
						"whats {inputValue} {sourceType} in {destType}",
						"what is {inputValue} {sourceType} in {destType}",
						"now give me {inputValue} {sourceType} in {destType}",
						"what about {inputValue} {sourceType} in {destType}"
					]
				},
				{
					"name": "WithDecimal",
					"slots": [
						{
							"name": "inputValue",
							"type": "AMAZON.NUMBER"
						},
						{
							"name": "decimalValue",
							"type": "AMAZON.NUMBER"
						},
						{
							"name": "sourceType",
							"type": "measuretype"
						},
						{
							"name": "destType",
							"type": "measuretype"
						}
					],
					"samples": [
						"what is {inputValue} point {decimalValue} {sourceType} in {destType}",
						"now give me {inputValue} point {decimalValue} {sourceType} in {destType}",
						"what about {inputValue} point {decimalValue} {sourceType} in {destType}",
						"whats {inputValue} point {decimalValue} {sourceType} in {destType}",
						"tell me {inputValue} point {decimalValue} {sourceType} in {destType}",
						"give me {inputValue} point {decimalValue} {sourceType} in {destType}",
						"convert {inputValue} point {decimalValue} {sourceType} to {destType}",
						"change {inputValue} point {decimalValue} {sourceType} to {destType}",
						"{inputValue} point {decimalValue} {sourceType} to {destType}",
						"{inputValue} point {decimalValue} {sourceType} into {destType}",
						"{inputValue} point {decimalValue} {sourceType} in {destType}",
						"for {inputValue} point {decimalValue} {sourceType} in {destType}"
					]
				}
			],
			"types": [
				{
					"name": "measuretype",
					"values": [
						{
							"name": {
								"value": "pulgadas",
								"synonyms": [
									"pulgada"
								]
							}
						},
						{
							"name": {
								"value": "pies",
								"synonyms": [
									"pie"
								]
							}
						},
						{
							"name": {
								"value": "yardas",
								"synonyms": [
									"yarda"
								]
							}
						},
						{
							"name": {
								"value": "millas",
								"synonyms": [
									"milla"
								]
							}
						},
						{
							"name": {
								"value": "milimetros",
								"synonyms": [
									"milimetro"
								]
							}
						},
						{
							"name": {
								"value": "centimetros",
								"synonyms": [
									"centimetro"
								]
							}
						},
						{
							"name": {
								"value": "metros",
								"synonyms": [
									"metro"
								]
							}
						},
						{
							"name": {
								"value": "kilómetros",
								"synonyms": [
									"kilómetro"
								]
							}
						}
					]
				}
			]
		}
	}
}